zran.cpython-311-x86_64-linux-gnu.so
zran/zranlib.c
zran/zran.pxd
zran/zran.h
zran/zranlib.pyx
zran/zran.c
zran-0.1.0.dist-info/RECORD
zran-0.1.0.dist-info/top_level.txt
zran-0.1.0.dist-info/METADATA
zran-0.1.0.dist-info/WHEEL
