Metadata-Version: 2.1
Name: zran
Version: 0.1.0
Summary: Utility for randomly accessing DEFLATE-compressed data
Author-email: Forrest Williams <ffwilliams2@alaska.edu>
Project-URL: Homepage, https://github.com/forrestfwilliams/zran
Project-URL: Bug Tracker, https://github.com/forrestfwilliams/zran/issues
Classifier: Intended Audience :: Developers
Classifier: License :: OSI Approved :: zlib/libpng License
Classifier: Natural Language :: English
Classifier: Operating System :: OS Independent
Classifier: Programming Language :: C
Classifier: Programming Language :: Python :: 3
Classifier: Programming Language :: Python :: 3.8
Classifier: Programming Language :: Python :: 3.9
Classifier: Programming Language :: Python :: 3.10
Classifier: Programming Language :: Python :: 3.11
Classifier: Programming Language :: Python :: 3 :: Only
Classifier: Programming Language :: Python :: Implementation :: CPython
Classifier: Operating System :: POSIX
Classifier: Operating System :: Unix
Classifier: Operating System :: MacOS
Requires-Python: >=3.8
